{
    "palette": "blue",
    "header": {
        "title": "Fjord",
        "tagline": "In it for the experience!",
        "logo_img": "images/test1.png",
        "logo_img_alt": "Swim Open Water",
        "background_img": "images/3.jpg",
        "has_nav": true,
        "nav_links": [
            {
                "label": "Home",
                "url": "/",
                "style": "link"
            },
            {
                "label": "About",
                "url": "/about",
                "style": "link"
            },
            {
                "label": "Style Guide",
                "url": "/style-guide",
                "style": "link"
            },
            {
                "label": "Contact",
                "url": "/contact",
                "style": "link"
            }
        ],
        "has_social": true,
        "social_links": [
            {
                "label": "Twitter",
                "url": "https://twitter.com/",
                "style": "icon",
                "icon_class": "twitter",
                "new_window": true
            },
            {
                "label": "Instagram",
                "url": "https://www.instagram.com/swimopenwater/",
                "style": "icon",
                "icon_class": "instagram",
                "new_window": true
            },
            {
                "label": "DEV",
                "url": "https://rossknight.co.uk",
                "style": "icon",
                "icon_class": "dev",
                "new_window": true
            }
        ]
    },
    "footer": {
        "content": ""
    },
    "title": "Swim Open Water"
}